timerit/__init__.py
timerit/core.py
timerit/core.pyi
timerit/py.typed
timerit/relative.py
timerit/relative.pyi
timerit-1.1.0.dist-info/LICENSE
timerit-1.1.0.dist-info/METADATA
timerit-1.1.0.dist-info/WHEEL
timerit-1.1.0.dist-info/top_level.txt
timerit-1.1.0.dist-info/RECORD
